cmlibs/__init__.py
cmlibs/importer/__init__.py
cmlibs/importer/base.py
cmlibs/importer/celldensity.py
cmlibs/importer/colonhrm.py
cmlibs/importer/colonmanometry.py
cmlibs/importer/dxf.py
cmlibs/importer/errors.py
cmlibs/importer/main.py
cmlibs/importer/mbfxml.py
cmlibs/importer/obj.py
cmlibs/importer/ply.py
cmlibs/importer/pointcloud.py
cmlibs/importer/ragpdata.py
cmlibs/importer/stl.py
cmlibs/importer/svg.py
cmlibs/importer/trimesh.py
cmlibs/importer/webgl.py
cmlibs/importer/xyz.py
cmlibs/importer/xyzvalue.py
cmlibs_importer-0.8.0.dist-info/licenses/LICENSE
cmlibs_importer-0.8.0.dist-info/METADATA
cmlibs_importer-0.8.0.dist-info/WHEEL
cmlibs_importer-0.8.0.dist-info/top_level.txt
cmlibs_importer-0.8.0.dist-info/RECORD
