Metadata-Version: 2.4
Name: cmlibs.importer
Version: 0.8.0
Summary: Import a variety of formats to CMLibs Zinc.
Author-email: Hugh Sorby <h.sorby@auckland.ac.nz>
License-Expression: Apache-2.0
Project-URL: Homepage, https://cmlibs.org
Project-URL: Repository, https://github.com/CMLibs-Python/cmlibs.importer
Keywords: Import,CMLibs,Zinc
Classifier: Programming Language :: Python :: 3
Classifier: Operating System :: OS Independent
Classifier: Topic :: Scientific/Engineering :: Medical Science Apps.
Requires-Python: >=3.8
License-File: LICENSE
Requires-Dist: cmlibs.utils
Requires-Dist: cmlibs.zinc>=4.2.0
Requires-Dist: pointpare
Provides-Extra: common
Requires-Dist: trimesh; extra == "common"
Requires-Dist: Shapely; extra == "common"
Provides-Extra: svg
Requires-Dist: trimesh; extra == "svg"
Requires-Dist: svg.path; extra == "svg"
Requires-Dist: lxml; extra == "svg"
Provides-Extra: mbfxml
Requires-Dist: mbfxml2ex>=0.8.4; extra == "mbfxml"
Provides-Extra: all
Requires-Dist: mbfxml2ex>=0.8.4; extra == "all"
Requires-Dist: svg.path; extra == "all"
Requires-Dist: lxml; extra == "all"
Requires-Dist: trimesh; extra == "all"
Requires-Dist: Shapely; extra == "all"
Dynamic: license-file
